fastapi_cbv/__init__.py
fastapi_cbv/_args.py
fastapi_cbv/app.py
fastapi_cbv/controller.py
fastapi_cbv/error.py
fastapi_cbv/global_dependency.py
fastapi_cbv/middleware.py
fastapi_cbv/routing.py
fastapi_cbv/utils/__init__.py
fastapi_cbv/utils/casing.py
fastapi_cbv-0.0.1.dist-info/LICENSE
fastapi_cbv-0.0.1.dist-info/METADATA
fastapi_cbv-0.0.1.dist-info/WHEEL
fastapi_cbv-0.0.1.dist-info/RECORD
