Metadata-Version: 2.1
Name: fastapi-cbv
Version: 0.0.1
Summary: This will help you to create class based view (aka controller) with FastAPI.
License: MIT
Author: 백세종
Author-email: sejong418@icloud.com
Requires-Python: >=3.11,<3.12
Classifier: License :: OSI Approved :: MIT License
Classifier: Programming Language :: Python :: 3
Classifier: Programming Language :: Python :: 3.11
Requires-Dist: dependency-injector (>=4.41.0,<5.0.0)
Requires-Dist: fastapi (>=0.95.2,<0.96.0)
